django_field_translate-0.1.3.dist-info/DESCRIPTION.rst
django_field_translate-0.1.3.dist-info/METADATA
django_field_translate-0.1.3.dist-info/RECORD
django_field_translate-0.1.3.dist-info/WHEEL
django_field_translate-0.1.3.dist-info/metadata.json
django_field_translate-0.1.3.dist-info/top_level.txt
field_translate/__init__.py
field_translate/widgets.py
field_translate/static/js/model_multi_choice_widget.js
field_translate/static/js/translate_checkbox_select_multiple.js
field_translate/templates/admin/attrs.html
field_translate/templates/admin/checkbox_option.html
field_translate/templates/admin/checkbox_select_with_lang.html
field_translate/templates/admin/input.html
field_translate/templates/admin/input_option.html
