Metadata-Version: 2.0
Name: django-field-translate
Version: 0.1.3
Summary: A simple Django app to filter objects related by language
Home-page: https://www.example.com/
Author: Pedro Reis
Author-email: pedro.reis@ongrace.com
License: BSD License
Platform: UNKNOWN
Classifier: Environment :: Web Environment
Classifier: Framework :: Django
Classifier: Framework :: Django :: 1.11
Classifier: Intended Audience :: Developers
Classifier: License :: OSI Approved :: BSD License
Classifier: Operating System :: OS Independent
Classifier: Programming Language :: Python
Classifier: Programming Language :: Python :: 2.7
Classifier: Topic :: Internet :: WWW/HTTP
Classifier: Topic :: Internet :: WWW/HTTP :: Dynamic Content
